shm_rpc_bridge/__init__.py
shm_rpc_bridge/client.py
shm_rpc_bridge/exceptions.py
shm_rpc_bridge/server.py
shm_rpc_bridge/_internal/__init__.py
shm_rpc_bridge/_internal/data.py
shm_rpc_bridge/transport/__init__.py
shm_rpc_bridge/transport/transport.py
shm_rpc_bridge/transport/transport_chooser.py
shm_rpc_bridge/transport/transport_futex.py
shm_rpc_bridge/transport/transport_posix.py
shm_rpc_bridge-0.2.4.dist-info/LICENSE
shm_rpc_bridge-0.2.4.dist-info/METADATA
shm_rpc_bridge-0.2.4.dist-info/WHEEL
shm_rpc_bridge-0.2.4.dist-info/top_level.txt
shm_rpc_bridge-0.2.4.dist-info/RECORD
